src/uds_lib/__init__.py
src/uds_lib/lib/__init__.py
src/uds_lib/lib/aws/__init__.py
src/uds_lib/lib/aws/aws_cognito.py
src/uds_lib/lib/aws/aws_cred.py
src/uds_lib/lib/aws/aws_lambda.py
src/uds_lib/lib/aws/aws_message_transformers.py
src/uds_lib/lib/aws/aws_param_store.py
src/uds_lib/lib/aws/aws_s3.py
src/uds_lib/lib/aws/aws_sns.py
src/uds_lib/lib/aws/es_abstract.py
src/uds_lib/lib/aws/es_factory.py
src/uds_lib/lib/aws/es_middleware.py
src/uds_lib/lib/aws/es_middleware_aws.py
src/uds_lib/lib/cognito_login/__init__.py
src/uds_lib/lib/cognito_login/cognito_login.py
src/uds_lib/lib/cognito_login/cognito_token_retriever.py
src/uds_lib/lib/constants.py
src/uds_lib/lib/cumulus_stac/__init__.py
src/uds_lib/lib/cumulus_stac/collection_transformer.py
src/uds_lib/lib/cumulus_stac/granules_catalog.py
src/uds_lib/lib/cumulus_stac/item_transformer.py
src/uds_lib/lib/cumulus_stac/stac_transformer_abstract.py
src/uds_lib/lib/cumulus_stac/stac_utils.py
src/uds_lib/lib/cumulus_stac/unity_collection_stac.py
src/uds_lib/lib/earthdata_login/__init__.py
src/uds_lib/lib/earthdata_login/urs_token.py
src/uds_lib/lib/earthdata_login/urs_token_retriever.py
src/uds_lib/lib/processing_jobs/__init__.py
src/uds_lib/lib/processing_jobs/job_executor_abstract.py
src/uds_lib/lib/processing_jobs/job_manager_abstract.py
src/uds_lib/lib/processing_jobs/job_manager_factory.py
src/uds_lib/lib/processing_jobs/job_manager_local_filesystem.py
src/uds_lib/lib/processing_jobs/job_manager_memory.py
src/uds_lib/lib/processing_jobs/multithread_processor.py
src/uds_lib/lib/utils/__init__.py
src/uds_lib/lib/utils/factory_abstract.py
src/uds_lib/lib/utils/fake_lock.py
src/uds_lib/lib/utils/file_utils.py
src/uds_lib/lib/utils/json_validator.py
src/uds_lib/lib/utils/lambda_api_gateway_utils.py
src/uds_lib/lib/utils/time_utils.py
src/uds_lib/stage_in_out/__init__.py
src/uds_lib/stage_in_out/catalog_granules_abstract.py
src/uds_lib/stage_in_out/catalog_granules_factory.py
uds_lib-0.1.1.dist-info/LICENSE
uds_lib-0.1.1.dist-info/METADATA
uds_lib-0.1.1.dist-info/WHEEL
uds_lib-0.1.1.dist-info/RECORD
